MANIFEST.in
README.md
bottle_marshmallow.py
setup.py
bottle_marshmallow.egg-info/PKG-INFO
bottle_marshmallow.egg-info/SOURCES.txt
bottle_marshmallow.egg-info/dependency_links.txt
bottle_marshmallow.egg-info/not-zip-safe
bottle_marshmallow.egg-info/requires.txt
bottle_marshmallow.egg-info/top_level.txt