Metadata-Version: 1.1
Name: bottle-marshmallow
Version: 1.0.3
Summary: marshmallow plugin for bottle
Home-page: https://github.com/agalera/bottle-marshmallow
Author: Alberto Galera Jimenez
Author-email: galerajimenez@gmail.com
License: GPL
Keywords: bottle-marshmallow
Platform: UNKNOWN
Classifier: Development Status :: 4 - Beta
Classifier: Topic :: Software Development :: Libraries :: Python Modules
Classifier: Intended Audience :: Developers
Classifier: License :: OSI Approved :: GNU General Public License (GPL)
Classifier: Natural Language :: English
Classifier: Programming Language :: Python :: 3
